{"cameraMode":{"drawMode":0,"name":"Shaded","section":"Shading Mode"},"sceneLighting":true,"audioPlay":false,"sceneViewState":{"showFog":true,"showMaterialUpdate":false,"showSkybox":true,"showFlares":true,"showImageEffects":true,"showParticleSystems":true},"in2DMode":false,"pivot":{"x":111.66495513916016,"y":36.310768127441409,"z":46.12877655029297},"rotation":{"x":-0.06679268181324005,"y":-0.8239148855209351,"z":0.5539246797561646,"w":-0.0993504449725151},"size":49.37106704711914,"orthographic":false}